{
    "filename": "1863-07-11_Amari_Michele",
    "title": "Ferdinand Gregorovius an Michele Amari in Turin. Turin, 11. Juli 1863",
    "sent": {
        "date": {
            "when": "1863-07-11",
            "cert": "high"
        },
        "person": {
            "name": "Gregorovius, Ferdinand (1821\u20131891)",
            "key": "G001200"
        },
        "place": {
            "name": "Turin",
            "key": "G000893"
        }
    },
    "received": null,
    "plain": "\n\n\n\nGentilissimo SignoreMichele Amari (1806\u20131889) war Historiker und Orientalist, Universit\u00e4tsprofessor f\u00fcr arabische Sprache (Pisa 1859, Florenz 1859 und 1864\u20131878) und Politiker. Nach dem Anschluss Siziliens an das K\u00f6nigreich Italien (1861) wurde er zum Senator ernannt, von 1862\u20131864 leitete er das Ministero dell\u2019Istruzione Pubblica (Dt.: Bildungsministerium). Gregorovius lernte Amari im September 1861 in Florenz kennen (siehe RT, 17.9.1861, S. 137). Eines der bedeutendsten, von Gregorovius sehr gesch\u00e4tzten Werke Amaris ist die \u201eStoria dei musulmani di Sicilia\u201c (3 Bde., Florenz: Le Monnier 1853\u20131873). Siehe \u201eSiciliana. Wanderungen in Neapel und Sizilien\u201c (1861), S. 93 sowie den Brief von Gregorovius an Theodor Heyse, 17.9.1855.,\n\nquanto mi dispiace, di non aver potuto ricevere la sua visita di ieri non so dirle; oggi devo partire alle 8 ore et mezzaVermutlich schrieb Gregorovius den Brief in Turin am Morgen des 11.7.1863, d. h. am Tag seiner Abreise nach M\u00fcnchen (siehe RT, 14.7.1863, S. 163).; devo dunque rinunciare a rivederla; ma spero di trovarla a Firenze nel mese di Settembre. Intanto mi potrebbe far il bene, di leggere questa acchiusavi carta; vorrei pur pregarla di scrivermi raccomandazioni per gli archivi di Bologna, di Napoli, e di SienaGregorovius erhielt von Amari Empfehlungen f\u00fcr die Archive in Bologna und Siena. Die Dokumente vom 12., 16. und 18.9.1863 (Bologna und Toskana) finden sich heute in Rom im Archivio Centrale dello Stato (Min. Pub. Istr., Personale 1860\u20131880, Gregorovius, busta 165). Im Tagebuch hei\u00dft es dar\u00fcber am 20.9.1863: \u201eIch fand Briefe Amaris auf der Post, die mich an den Grafen Carlo Pepoli [Conte Carlo Pepoli (1796\u20131881)] empfahlen, den Syndikus Bolognas\u201c (S. 168) und am 4.10.1863: \u201eAmari hatte mich von Turin aus empfohlen\u201c (S. 170).. Di questo potrei scriverle da Monaco, per dove parto.\n\nIo la saluto di cuore,\nGregorovius.\n\n\n"
}