{
    "filename": "1864-02-23_Thile_Hermann",
    "title": "Ferdinand Gregorovius an Hermann von Thile in Berlin. Rom, 23. Februar 1864",
    "sent": {
        "date": {
            "when": "1864-02-23",
            "cert": "high"
        },
        "person": {
            "name": "Gregorovius, Ferdinand (1821\u20131891)",
            "key": "G001200"
        },
        "place": {
            "name": "Rom",
            "key": "G000763"
        }
    },
    "received": null,
    "plain": "\n\n\nRom, 23. Februar 1864.\n\nHaben Sie, mein hochverehrter Herr, tausend Dank f\u00fcr Ihr g\u00fctiges Schreiben, dessen Wert die \u00dcberf\u00fclle Ihrer Gesch\u00e4fte mir verzehnfachen mu\u00df. Ich sehe der Entscheidung wegen des verl\u00e4ngerten Subsidien-Tractats mit ZuversichtAuf Vermittlung Thiles erhielt Gregorovius vom Kultusministerium der preu\u00dfischen Regierung seit Herbst 1860 ein Stipendium zur Fertigstellung seiner \u201eGeschichte der Stadt Rom im Mittelalter\u201c (siehe den Brief von Gregorovius an Thile, 9.8.1860). entgegen, da diese Angelegenheit in Ihren H\u00e4nden ist, und w\u00fcnsche nur, sie m\u00f6chte Ihnen nicht bereits zu sehr Geduld- und Zeitraubend gewesen sein. Doch ist das echte Wolwollen ein Ding au\u00dferhalb der Zeitrechnung, und dem Verlust nicht ausgesetzt. Die Erinnerung der Frau KronprinzessinDie Frau des preu\u00dfischen Kronprinzen Friedrich Wilhelm (1831\u20131888) seit 1858, Prinzessin Victoria von Gro\u00dfbritannien und Irland (1840\u20131901), eine Tochter von K\u00f6nigin Victoria (1819\u20131901), die Gregorovius im Dezember 1862 in Rom kennengelernt hatte (siehe RT, 14.12.1862, S. 156 und den Brief von Gregorovius an Thile, 30.8.1863). zeigt ein k\u00f6nigliches Gem\u00fct; der Himmel mag es lohnen; mich hat es sehr erfreut. Ich sage unterde\u00df, was der alte Ricordano Malaspini gesagt hat: buono studio rompe rea fortunaItal.: Gutes Studium bricht das Gl\u00fcck, nach: Storia fiorentina di Ricordano Malispini [etwa 1220-etwa 1290]: dall\u2019 edificazione di Firenze fino al 1282. Seguitata poi da Giacotto Malispini fino al 1286. Bd. 2. Livorno 1830. S. 419.. Ich bin mit meiner m\u00e4\u00dfigen Lage zufrieden, welche durch v\u00f6llige Freiheit und eine mir homogene Th\u00e4tigkeit erweitert und befestigt wird. Auch bricht sich die Geschichte der Stadt, trotz mancher Mi\u00dfgunst, immer weiter Bahn; der Verkauf des Buchs ist gut, und verhei\u00dft in wenigen Jahren eine neue AuflageGregorovius arbeitete am f\u00fcnften Band seiner \u201eGeschichte der Stadt Rom im Mittelalter\u201c (1865). Die \u201eZweite durchgearbeitete Auflage\u201c des ersten Bandes (1859) erschien 1869 \u2013 drei Jahre vor dem Erschienen des achten und letzten Bandes (1872).. Man hat mir aus England und Frankreich \u00dcbersetzungsantr\u00e4ge gemachtEine franz\u00f6sische \u00dcbersetzung seiner \u201eGeschichte der Stadt Rom im Mittelalter\u201c ist bis heute nicht angefertigt worden; eine englische \u00dcbersetzung erschien erst nach dem Tod von Gregorovius: History of the City of Rome in the Middle Ages. Translated from the Fourth German edition by Annie Hamilton. 8 Bde. in 13. London: Bell & Sons 1894\u20131902.; sie werden wol ein Resultat haben, wenn die Zeitverh\u00e4ltni\u00dfe ruhiger geworden sind. Beim Prinzen Ludovisi entdeckte ich eine prachtvolle historische Bibliothek; dieser edle Nepot Gregor\u2019s XV ist liberal genug, mir sie massenweise ins Haus zu schickenDer schwerreiche italienische Mathematikhistoriker Baldassarre Boncompagni (1821\u20131894) war Nachfahre von Alessandro Ludovisi (1554\u20131623), 1621\u20131623 Gregor XV. Siehe RT, 24.1.1864, S. 175.. Sie erinnern sich seiner ohne Zweifel; er steckt eine gro\u00dfe Rente in seine B\u00fccher, und besch\u00e4ftigt sich viel mit Mathematik. Er hat einen alten Mathematiker, Leonardus Pisanus, herausgegebenBaldassare Boncompagni widmete sich der Erforschung von Fibonacci (Leonardo von Pisa, 1175\u20131250), \u00fcber den er 1852 eine Biographie publiziert hatte. 1854 hatte er seine Werke mit Faksimiles herausgegeben (Intorno ad alcune opere di Leonardo Pisano: mathematico del secolo del secolo decimoterzo. Notizie Raccolte di Baldassarre Boncompagni. Rom 1854). In der Biblioteca Ambrosiana in Mailand hatte er verschollen geglaubte und unbekannte Manuskripte von Fibonacci (Liber Quadratorum, Flos) entdeckt und gab sie, mit Erg\u00e4nzungen des Turiner Juristen und Mathematikers Angelo Genocchi (1817\u20131889), heraus (Opuscoli di Leonardo Pisano, 2. Auflage 1856). Boncompagni trug eine riesige Privatbibliothek von 600 Manuskripten und 20 000 B\u00fcchern zusammen (der Katalog wurde von seinem Sekret\u00e4r Enrico Narducci 1862 und 1892 publiziert), die nach seinem Tod zerstreut und versteigert wurde.. \nIhre Sehnsucht nach Rom verst\u00e4rkt meinen Mut, hier zu leben, und meine Studien machen dies zur Pflicht. Doch ist es schmerzlich, dem Vaterland heute fern zu sein, wo vielleicht die Entscheidung \u00fcber unsere politische Zukunft fallen wirdNach dem Versuch D\u00e4nemarks mit der Novemberverfassung 1863 Schleswig an das d\u00e4nische K\u00f6nigreich anzuschlie\u00dfen, hatte sich Preu\u00dfen mit \u00d6sterreich verb\u00fcndet. Am 1. Februar 1864 hatte der Deutsch-D\u00e4nische Krieg begonnen, der am 30. Oktober 1864 mit dem Sieg der preu\u00dfisch-\u00f6sterreichischen Truppen und einer gemeinsamen Verwaltung von Schleswig-Holstein endete.. Dies regt uns alle sehr auf; nur das Wunder des Telegraphen macht das Leben in der Fremde unter diesen Verh\u00e4ltni\u00dfen ertr\u00e4glich. Wenn ich bedenke, welche gro\u00dfe Weltb\u00fcrde Deutschland in den langen Jahrhunderten des Reichs getragen hat, so wei\u00df ich nicht, ob unser Vaterland noch berufen ist, eine andre gro\u00dfe politische Rolle zu spielen, oder ob es nicht sein Pulver mit der Reformation verscho\u00dfen hat, und nun nichts mehr sein kann, als der gro\u00dfe akademische Hain Europas, und die StoaDie von dem griechischen Philosophen Zenon von Kition (333/332\u2013262/261 v. Chr.) in Athen begr\u00fcndete Schule, nach der mit Gelassenheit und Seelenruhe nach Weisheit zu streben ist. wissenschaftlicher lieber Discussionen. Sehr traurig stimmt uns hier die dreifache ZerrissenheitM\u00f6glicherweise Anh\u00e4nger des Papsttums, des K\u00f6nigreichs und der Republik?, f\u00fcr welche nirgend Heilung sichtbar ist.\nWir leben hier in Rom wie auf einer Insel fort. Wie sich hier die Dinge l\u00f6sen werden, ist ein tiefes R\u00e4tsel, und wol aller menschlichen Teilnahme wert. Der Papst ist heiter und wol, so sagt man. Aber seine Jahre sind gez\u00e4hltPius IX. (1792\u20131878) war von 1846 bis 1878 Papst, 31 Jahre und 8 Monate. ; nach dem alten Gesetz p\u00e4pstlicher Epochen hat er h\u00f6chstens nur noch 6 Jahre vor sich. Non habebis annos Petri.Lat.: Du erreichst nicht die (Regierungs-)Jahre des Petrus. Das Ponifikat des Heiligen Petrus soll 34 Jahre (33\u201367) gedauert haben \u2013 einer Legende nach 25 Jahre. \nSie w\u00fcrden Rom in Folge der Eisenbahnen, welche unerquickliche Gasthausschw\u00e4rme von immer fl\u00fcchtigeren Menschen auf die Stra\u00dfen werfen, ziemlich ver\u00e4ndert finden. Man baut oder restaurirt viel. Eine pr\u00e4chtige Drahtbr\u00fcckeDer 1861 bis1863 am \u00f6stlichen Tiberufer errichtete Ponte dei Fiorentini (siehe https://it.wikipedia.org/wiki/Ponte_dei_Fiorentini#/media/File:Iron_bridge_at_San_Giovanni_dei_Fiorentini,_ca._1890.jpg) sollte eine zus\u00e4tzliche Verbindung zwischen dem historischen Zentrum und dem im Bau befindlichen Viertel von Prati schaffen. 1941 wurde die Br\u00fccke zerst\u00f6rt und im Jahr darauf durch den Ponte Principe Amedeo Savoia Aosta ersetzt. f\u00fchrt jetzt vom Palast SalviatiDer in der ersten H\u00e4lfte des 16. Jahrhunderts, nach Pl\u00e4nen von Giulio Romano (1499\u20131546), f\u00fcr Papst Leo X. (1475\u20131521) errichtete Palast. in der Longara nach San Giovanni dei FiorentiniDie im 16. Jahrhundert von Papst Leo X. de\u2019 Medici (1513\u20131521) gegr\u00fcndete und erst von Giuliano da Sangallo (um 1445\u20131516) und dann von Giacomo della Porta (1532\u20131602) begonnene Basilika. Fertiggestellt wurde sie erst im 18. Jahrhundert und ist die Nationalkirche der Florentiner Gemeinde in Rom.. Man ist sogar reinlicher geworden. Die Caf\u00e9s und Trattorien werden hie und da elegant. Ihr Capitol hat sich nicht ver\u00e4ndert; nur die gro\u00dfe Treppe hat ihre Ziegelsteine von Opus spicatumLat.: Schr\u00e4g wie \u00c4hren verlegte Steine. verloren, und ist jetzt mit Asphaltplatten gepflastert. Zugleich hat man den Raum zwischen ihr und der Treppe von AraceliDie im 13. Jahrhundert errichtete, gro\u00dfe, dreischiffige S\u00e4ulenbasilika Santa Maria in Aracoeli liegt auf dem Kapitolsh\u00fcgel neben dem Capitol und wurde im Mittelalter als Stadtparlament und Gerichtsst\u00e4tte genutzt. Sie ist \u00fcber die steile, charakteristische Scalinata di Aracoeli erreichbar. in einen sch\u00f6nen, kleinen Garten verwandelt. Herr von Willisen scheint sich mit Rom mehr befreundet zu haben, als mit den R\u00f6mern; auf seinen zahlreich besuchten Mitwochsabenden sieht man deren keineDer preu\u00dfische General Friedrich Adolf Freiherr von Willisen (1798\u20131864) war im Juli des Vorjahres erster Gesandter der preu\u00dfischen Staatsregierung am italienischen K\u00f6nigshof geworden. Er war mit Pauline, geb von Brause (1815\u20131880), verheiratet. Die \u201eMittwochs Soireen beim Gesandten\u201c hielt Gregorovius auch in seinem Tagebuch fest (22.11.1863, S. 173; siehe auch die Briefe von Gregorovius an Thile, 16.6.1863 und 27.12.1863)., es sei denn hie und da einen wankenden Cardinal. \nWir hatten auch hier harten Winter, bis zu 4\u00b0 unter Null, am 9. Februar sogar tiefen Schnee, und Schneeballiren auf dem Pincio, wo r\u00f6mische Rotten mit Eisb\u00e4llen um Mittagszeit Spazierg\u00e4nger, Wachen und Gensdarmen vertrieben \u2013 eine hier kaum gesehene Erscheinung. Es st\u00fcrmt und regnet. Das Elend auf der Campagna ist sehr gro\u00df.\nIch sehe mit Schrecken, da\u00df mein Brief \u00fcber Geb\u00fchr lang geworden ist, und bitte um Verzeihung. M\u00f6chten Sie jetzt bessere Gesundheit genie\u00dfen, und mehr Erholung von Ihrer m\u00fchevollen Th\u00e4tigkeit finden. Ich empfehle mich dem Wolwollen Ihrer Frau Gemalin, und gr\u00fc\u00dfe herzlich Ihren jetzt schon gro\u00dfen Sohn, der wol bald als Studiosus hoher Wissenschaften umherstolziren wird.\n\nMit herzlicher Verehrung Ihr\nFGregorovius.\nIch verga\u00df zu sagen, da\u00df ich nicht in Verlegenheit bin \u2013 mein Finanzministerium ist bis zum Sommer wolversorgt; ich verga\u00df nicht, mit Besch\u00e4mung, mich meiner Fehler wie Schulden zu erinnern; diese dr\u00fccken mich nicht so wie jene, doch setzt mich bald wol ein Gewinn, wovon ich mir sp\u00e4ter zu schreiben erlaubeGregorovius hatte bei Thile, vor dessen Weggang aus Rom, Schulden gemacht. Siehe die Briefe von Gregorovius an Thile, 22.12.1858, 11.4.1859 und 11.1.1860 (in: Briefe von Ferdinand Gregorovius an den Staatssekret\u00e4r Hermann von Thile. Hrsg. von Herman von Petersdorff. Berlin 1894. S. 20\u201323). Im nachfolgenden Schreiben an Thile vom 17.5.1864 berichtet Gregorovius von seinem Erbe von 2000 Taler von einer nicht namentlich genannten Dame., in den Stand, meine Pflicht zu erf\u00fcllen, gegen welche Sie so nachsichtig sind.\n\n"
}