{
    "filename": "1867-04-30_Caetani_Lovatelli_Ersilia",
    "title": "Ferdinand Gregorovius an Contessa Ersilia Caetani Lovatelli in Rom. Rom, 30. April 1867",
    "sent": {
        "date": {
            "when": "1867-04-30",
            "cert": "high"
        },
        "person": {
            "name": "Gregorovius, Ferdinand (1821\u20131891)",
            "key": "G001200"
        },
        "place": {
            "name": "Rom",
            "key": "G000763"
        }
    },
    "received": null,
    "plain": "\n\n\nVerehrte Frau Gr\u00e4fin,\n\nSie haben mich hoch erfreut durch Ihre wohlgetroffene PhotographieDie Gr\u00e4fin bedankt sich mit ihrem Bild f\u00fcr seine, ihr Ende Dezember 1866 zugesandte Photographie (siehe den Brief von Gregorovius an Ersilia Caetani Lovatelli, 31.12.1866).. Sie wird bei mir dauernd sein als ein geweihtes Andenken edler und guter Tage von Rom und mich freundlich an Sie gemahnen, wenn ich nicht mehr hier binErst 1874 sollte er Rom endg\u00fcltig verlassen (vgl. RT, S. 342\u2013343).. Ich danke Ihnen wahrhaft und darum nur mit diesen wenigen Worten. Ich bitte Sie, dies kleine Buch zum Zeichen meiner Verehrung gegen Sie aufzunehmenGregorovius legte dem Brief eine Ausgabe seines \u201eEuphorion\u201c (Leipzig: Brockhaus 1858) bei. Zu der Versdichtung war Gregorovius im Sommer 1853 bei einem Besuch in Neapel und Pompeji angeregt worden. Sie erz\u00e4hlt eine Liebesgeschichte im Schatten des Untergangs der Stadt Pompeji. Zun\u00e4chst begann Gregorovius im Januar 1854 mit einer Prosanovelle, die den Titel \u201eDer bronzene Kandelaber\u201c trug (siehe RT, 31.1.1854, S. 53), sp\u00e4ter empfohl er sie Brockhaus als \u201eEine Dichtung aus Pompeji in vier Ges\u00e4ngen\u201c zur Publikation (siehe den Brief von Gregorovius an Heinrich Brockhaus, 22.4.1855). . Ich w\u00fcnschte, es w\u00e4re werthvoller und Ihrer w\u00fcrdiger. Aber wie dem, in dessen Seele die Musik eingeboren ist, nur ein paar Accorde gen\u00fcgen, um sich eine ganze Welt von T\u00f6nen hervorzuzaubern, so werden auch f\u00fcr Ihren Geist diese d\u00fcrftigen Verse hinreichen, die Welt der antiken Sch\u00f6nheit sich klarer hervorzurufen, als ich sie auszusprechen vermochte. Ihnen und Ihrem ganzen edlen HauseAuch mit Ersilias Vater, dem Herzog von Sermoneta und Dante-Forscher Michelangelo Caetani (1804\u20131882), stand Gregorovius in vertrautem Kontakt.  sendet den Maiengru\u00df und w\u00fcnscht sonnige Tage immerdar Am letzten April 1867. \n\nGregorovius\n\n\n"
}