{
    "filename": "1872-08-21_Gozzadini_Giovanni",
    "title": "Ferdinand Gregorovius an Conte Giovanni Gozzadini in Bologna. Traunstein, 21. August 1872 ",
    "sent": {
        "date": {
            "when": "1872-08-21",
            "cert": "high"
        },
        "person": {
            "name": "Gregorovius, Ferdinand (1821\u20131891)",
            "key": "G001200"
        },
        "place": {
            "name": "Traunstein",
            "key": "G000888"
        }
    },
    "received": null,
    "plain": "\n\n\nTraunstein di Baviera 21. Agosto 1872\nGentilissimo signor Conte,\n\nMi affretto di ringraziarla di vero cuore della sua amabile lettera, speditami via Stuttgard a questo luogo di montagna.\nIo vedo con sommo piacere, che Ella e la signora Contessa gentilmente partecipano ai sentimenti di gioja, di cui sono presi tutti i miei amici a cagione dell\u2019onore compartito alla mia opera dal Municipio di RomaAm 13. Juli 1872 hatte der r\u00f6mische Gemeinderat dem Antrag des Marchese Francesco Nobili-Vitelleschi (1829\u20131906) auf Kosten\u00fcbernahme der Vollendung der italienischen \u00dcbersetzung der \u201eGeschichte der Stadt Rom im Mittelalter\u201c einstimmig stattgegeben. Renato Manzato (1847\u20131925) hatte die \u00dcbersetzung 1866 begonnen, Gregorovius deren Fortsetzung jedoch aufgrund ihrer Qualit\u00e4t verboten; siehe dazu den Brief von Gregorovius an Giovanni Gozzadini vom 24.2.1867. Der auf den 17. August 1872 datierte Vertrag zwischen der Stadt Rom und dem venezianischen Verlag Giuseppe Antonellil \u00fcber die Weiterf\u00fchrung der italienischen Ausgabe der \u201eGeschichte der Stadt Rom im Mittelalter\u201c hat sich im Nachlass von Gregorovius erhalten; des weiteren eine auf den 20. September 1872 datierte Verpflichtungserkl\u00e4rung von Antonelli gegen\u00fcber Gregorovius zur termingerechten Ver\u00f6ffentlichung der einzelnen B\u00e4nde der italienischen \u00dcbersetzung (BSB M\u00fcnchen, NL Gregorovius, Gregoroviusiana 26). Siehe dazu den Brief von Gregorovius an den r\u00f6mischen B\u00fcrgermeister Pietro Venturi vom 17. August 1872, mit dem er auf die erfreuliche Nachricht reagierte. . Difatti egli \u00e8 un onore insolito negli annali della letteratura, e perci\u00f2 tanto, da rendermene veramente confuso. Ma voglio lasciare da parte i sentimenti, e piuttosto parlare degli effetti reali, fra cui il maggiore sarebbe per me, la certezza, che oramai la stampa dell\u2019opera vera italiana \u00e8 assicurata. Quando tutti gli otto volumi che la compongono, saranno messi in circolazioneDen letzten Band hatte er am 19. Januar 1871 zu seinem 50. Geburtstag abgeschlossen; siehe den Brief von Gregorovius an Ottilie Elgnowski vom 4.12.1870; BSB M\u00fcnchen, NL Gregorovius, Gregoroviusiana 20. Ende November war der Band fertig gedruckt und konnte ausgegeben werden; siehe den Brief von Gregorovius an Albert Freiherr von Reischach vom 17.11.1872; DLA Marbach, Cotta-Archiv, Cotta-Briefe (154) (154). , allora spero che posseder\u00f2 in essi il modo di ringraziare gli Italiani dell\u2019accoglienza fraterna, di cui onorano l\u2019opera e me, l\u2019autore di essa. Che malgrado la insufficienza delle mie forze e i difetti che ne risultano, vi si troveranno pure le fondamenta di una storia civile della Citt\u00e0, che manca ancora. \nDa parecchie settimane mi sono stabilito a Traunstein, piccolo paese nelle vicinanze di Salisbourg, delizioso per bellezza di natura e per purezza dell\u2019aria. Faccio qui i bagni di salina, per curarmi definitivamente dal residuo di un raffreddore, preso nell\u2019inverno passato. Vi rester\u00f2 ancora qualche tempo, quindi far\u00f2 di altri viaggi nella Germania meridionaleGregorovius war am 14. Juli in Traunstein eingetroffen, wo er bis zum 12. September 1872 blieb: \u201eDiesen Ort w\u00e4hlte ich auf Anraten des Dr. [Franz] Seitz [(1811\u20131892)], um dasselbst Salzb\u00e4der zu gebrauchen.\u201c In M\u00fcnchen blieb er bis zum 12. November, kehrte von dort nach Italien zur\u00fcck (RT, 10.9.1872, S. 325\u2013327). . \nEbbi lettere di Frascati, che descrivono lo stato di salute della Duchessa di Sermoneta come disperato. Vi sta in villeggiatura tutta Mit der r\u00f6mischen Adelsfamilie Caetani, Michelangelo Caetani (1804\u20131882), Herzog von Sermoneta, und dessen Tochter Ersilia Caetani Lovatelli (1804\u20131925), war Gregorovius gut befreundet. Diese besa\u00df in der Gemeinde Frascati, 21 Kilometer s\u00fcd\u00f6stlich von Rom, ein Haus, in der sie auch Gregorovius mehrere Male besuchte (siehe RT, 6.10.1867, S. 234; 13.10.1867, S. 235; 28.7.1871, S. 308). Der Herzog war seit 1854 in zweiter Ehe mit Margaret Knight (*1810) verheiratet. Deren schlechter Gesundheitszustand war bereits in fr\u00fcheren Briefen Thema; siehe den Brief von Gregorovius an Ersilia Caetani Lovatelli vom 31.8.1868. Die Herzogin verstarb am 19. Oktober 1872.la famiglia Gaetani. Di Paolo non ebbi ancora notizie: gli scriver\u00f2 fra giorni.\nSpero che Lor Signorie si trovino in perfetta salute, e che non patiscano punte del caldo, il quale in Roma doveva essere pressoch\u00e8 insopportabile.\nS\u2019io posso esser utile a Loro durante la mia dimora in Germania, mi comandino, prego: il mio indirizzo sarebbe sempre quello della libreria Cotta a Stuttgard.\n\nIntanto mi raccomando alla Loro benevola memoria, pregiandomi di chiamarmi il di Loro verace servitore\n Gregorovius \n\n\n"
}