{
    "filename": "1873-12-07_Guasti_Cesare",
    "title": "Ferdinand Gregorovius an Cesare Guasti in Florenz. Rom, 7. Dezember 1873",
    "sent": {
        "date": {
            "when": "1873-12-07",
            "cert": "high"
        },
        "person": {
            "name": "Gregorovius, Ferdinand (1821\u20131891)",
            "key": "G001200"
        },
        "place": {
            "name": "Rom",
            "key": "G000763"
        }
    },
    "received": null,
    "plain": "\n\n\nRoma, Via Gregoriana numero 13. 7. Decembre 1873.\nEgregio e gentilissimo SignoreBereits im April diesen Jahres hatte Gregorovius den Assistenten im Florentiner Staatsarchiv, Cesare Guasti (1822\u20131889), wegen seiner Fragen zu Schriftst\u00fccken im Archiv kontaktiert; siehe den Brief von Gregorovius an Cesare Guasti vom 26.4.1873.,\n\nun giovane compatriota mio di G\u00f6ttingen si \u00e8 diretto a me, onde richiedermi della mia intercessione in favor suo, rispetto a certe sue domande. EgliNicht ermittelt, um wen es sich hier handelt., discepolo del WaitzDer Rechtshistoriker und Medi\u00e4vist Georg Waitz (1813\u20131886) war ein Sch\u00fcler von Leopold von Ranke (1795\u20131886) und arbeitete ab 1842 bei den \u201eMonumenta Germaniae Historica\u201c mit. Im selben Jahr wurde er von der Uni Kiel zum Professor berufen, 1848 ging er an die G\u00f6ttinger Universit\u00e4t, gr\u00fcndetet dort das Historische Seminar mit. 1875, als Pr\u00e4sident der \u201eMonumenta Germaniae Historica\u201c, kehrte er nach Berlin zur\u00fcck. Er war wesentlich an der \u201eQuellenkunde der deutschen Geschichte\u201c beteiligt. Gregorovius lernte ihn, \u201e[...] einen staatlichen Mann von gr\u00f6\u00dferer Art, als sonst deutsche Professoren zu haben pflegen\u201c, im November 1872 in M\u00fcnchen kennen (RT, 11.11.1873, S. 327). , sta scrivendo un lavoro, sulle relazioni, che correvano fra Arrigo VII. Imperatore e Papa Clemente, e il Re di NapoliHeinrich VII. (1278/79\u20131313), seit 1312 r\u00f6misch-deutscher Kaiser, Papst Clemens V. (zw. 1250 u. 1265\u20131314) und Robert von Anjou (1278\u20131343), K\u00f6nig von Neapel (1309\u20131343). Im Jahre 1310 unternahm Heinrich VII. einen Italienzug mit dem Zweck, sich die Kaiserkrone zu sichern. Nach Friedrich II. (1194\u20131250) war er der erste r\u00f6misch-deutsche K\u00f6nig, welcher die Kaiserkrone empfing. In seiner Position als Kaiser geriet er schnell in Auseinandersetzung mit dem papsttreuen K\u00f6nig von Neapel und den guelfischen Kr\u00e4ften Italiens. Papst Clemens V. hatte zun\u00e4chst mit dem Kaiser kooperiert, stellte sich nun aber an die Seite K\u00f6nig Roberts. Die von Heinrich auf eine Befriedung der zerstrittenen Gruppen Italiens ausgerichtete Politik, hatte keinen Erfolg, weil sowohl die Ghibellinen als auch die Guelfen auf eine politische Entwicklung zu ihren Gunsten pochten.. Avendo pero da quella parte della mia Storia di Roma, che ne trattaGeschichte der Stadt Rom im Mittelalter. Band 6. Stuttgart: Cotta 1867, bes. S. 26\u2013109. Zur \u00dcberlassung der Dokumente vor Drucklegung durch Bonaini: siehe ebenda, S. 32, Anm. 1., l\u2019avviso, che vi siano stampati alcuni fogli dei Regesta di codesto Imperatore per cura del benemerito BonainiFrancesco Bonaini (1806\u20131874) war Historiker und Archivar sowie Generalintendant der toskanischen Staatsarchive. Er war zudem entscheidender Vertreter der historischen Bewegung in Florenzf. Bonaini bildete zahlreiche j\u00fcngere Archivare und Pal\u00e4ographen aus. Gregorovius kannte ihn bereits seit September 1858, hatte ihn in Florenz \u00fcber Jean Jacques Amp\u00e8re (1800\u20131864) kennengelernt (siehe RT, 13.9.1858, S. 74). 1877 publizierte er die hier angesprochenen Regesten: Acta Henrici VII. Romanorum imperatoris et monumenta quaedam alia suorum temporum historiam illustrantia. 2 Bde. Florenz: Typis Galileianis M. Cellinii et soc., fogli che questi colla massima liberalit\u00e0 mi aveva prestato, diversi anni fa, quel giovane premurosamente mi prega, di far s\u00ec, che anche a lui venga concesso il medesimo favor, goduto da me stessoAus sp\u00e4teren Briefen von Gregorovius an Guasti geht hervor, dass die Anfrage positiv beantwortet wurde und der junge G\u00f6ttinger Forscher die gew\u00fcnschten Kopien erhielt; siehe die Briefe von Gregorovius an Cesare Guasti vom 13.12.1873 und vom 18.1.1874.. Non posso quindi far a meno, di ajutare quel giovane col dirigerle la domanda , se vi sia caso, di puoter presltargli quei fogli stampati, accioch\u00e8 egli se ne serva a proposito suo. Ci\u00f2 fatto, egli restituer\u00e0 sollecitamente il prestito. Credo, che gli originali stessi, sopra cui il Bonaini copi\u00f2 il Regesta, non stanno pi\u00f9 a Firenze, ma s\u00ec al palazzo Gambacorta di PisaDer zwischen 1370\u20131392 errichtete Palast der Familie Gambacorti, die dem reichen Handesladel in Pisa angeh\u00f6rten. Im 19. Jahrhundert hatte das Archivio di Stato seinen Sitz dort, was die \u00dcberf\u00fchrung der besagten Regesten von Heinrich VII. als gut m\u00f6glich erscheinen l\u00e4sst..\nElla scuser\u00e0 questo lieve disturbo ovvero incommodo colla sua solit\u00e0 gentilezza. Pregandola alla fine, di farmi sapere con due righe quello che avr\u00f2 da rispondere al giovane sopraaccenato, mi protesto colla pi\u00fa sincera considerazione e stima \n\ndi lei il servitor devoto\nFGregorovius.\n\n\n"
}