{
    "filename": "1875-06-16_Gozzadini_Giovanni",
    "title": "Ferdinand Gregorovius an Conte Giovanni Gozzadini in Bologna. Rom, 16. Juni 1875 ",
    "sent": {
        "date": {
            "when": "1875-06-16",
            "cert": "high"
        },
        "person": {
            "name": "Gregorovius, Ferdinand (1821\u20131891)",
            "key": "G001200"
        },
        "place": {
            "name": "Rom",
            "key": "G000763"
        }
    },
    "received": null,
    "plain": "\n\n\nRoma, 16. Giugno 1875.\nGentilissimo signor Conte,\n\nle rendo mille grazie del prezioso dono, che nuovamente mi ha fatto, destinandomi una copia dell\u2019ultima sua opera, scritta in lingua francese. Io ammiro la sua attivit\u00e0, rallegrandomene intimamente, e potrei dire anche vergognandomi nello stesso tempo di quella pigrizia, in cui pur troppo mi trovo immerso. Ch\u00e8 per verita non ho fatto nulla qu\u00ec, che meriti il sacro nome del lavoro. Feci si un viaggio nelle province meridionaliEr war vom 1.-21. Mai durch Apulien gereist (siehe RT, 23.5.1875, S. 351\u2013355), vornehmlich um die mit der Hohenstauffer-Zeit verbundenen Monumente zu besichtigen. Allerdings wurde sein, auf einer seinem Brief vom 24.9.1874 beigelegten f\u00fcnfseitigen Liste beruhender Plan mit den einzelnen \u201eIllustrationen zu den Geschichtlichen Denkm\u00e4lern der Hohenstaufen in Italien\u201c von Barbarossa bis Conradin (DLA Marbach, Cotta-Archiv, Cotta-Briefe, 208 und 208a \u2013 ohne die Beilagen gedruckt in: Johannes H\u00f6nig: Ferdinand Gregorovius der Geschichtsschreiber der Stadt Rom. Stuttgart, Berlin 1921. S. 367\u2013368) von Cotta aus Kostengr\u00fcnden abgelehnt. Die f\u00fcr das Album vorgesehenen Texte wurden von Gregorovius im 5. Band der \u201eWanderjahre in Italien\u201c (1877) zusammengefasst. Im Vorwort dieses Bandes hei\u00dft es dazu: \u201eIch wollte n\u00e4mlich ein Album historischer Landschaften und Monumente in Italien herausgeben, bez\u00fcglich auf die Geschichte der Hohenstaufen. Zu diesem Zweck hatte ich mich mit meinem Freunde Karl Lindemann vereinigt, welcher die betreffenden Zeichnungen zu liefern \u00fcbernommen hatte, und von seiner bew\u00e4hrten Meisterhand konnte nur etwas wirklich Sch\u00f6nes und K\u00fcnstlerisches erwartet werden. Diesen Plan hindert noch die Kostspieligkeit des Unternehmens, oder der Druck, welcher augenblicklich auf allen gr\u00f6\u00dferen Unternehmungen auch solcher Natur lastet. Ich glaube, da\u00df dies zu bedauern ist. Wenigstens sollten wir Deutsche ein Werk dieser Art besitzen.\u201c  dell\u2019Italia, affine di conoscere alcuni monumenti e locali, che sono conservati alla memoria della casa degli Hohenstauffen, e rovistai un po\u2019 nelle carte dell\u2019Archivio di Stato, che si sta formando attualmente in RomaDie aus den s\u00e4kularisierten Kl\u00f6stern entwendeten Bibliotheken und Dokumentsammlungen gingen in das 1871 gegr\u00fcndete Archivio di Stato di Roma ein. Gregorovius verfasste dazu in der \u201eHistorischen Zeitschrift\u201c einen Aufsatz mit dem Titel \u201eDas R\u00f6mische Staatsarchiv\u201c (Bd. 36. M\u00fcnchen: Oldenbourg 1876. S. 141\u2013178).. \nOra la mi dimora qu\u00ec volge alla sua fine; ritorner\u00f2 in patria dopo quindici giorni, per riunirmi colla mia famiglia in MonacoEr verlie\u00df Rom am 28. Juni und reiste \u00fcber Kufstein und Traunstein, wo er zwei Monate blieb, nach M\u00fcnchen. Dort traf er am 1. September ein (siehe RT, 1.3.1875, S. 359). Am 10. September 1874 hatte er sich dort mit seinem Bruder Julius (1819\u20131891) und ihrer gemeinsamen Halbschwester Ottilie (1834\u20131907) niedergelassen; siehe den Brief von Gregorovius an Raffaele Mariano vom 20.9.1874.. Quantunque io abbia dato fine a quegli studi storici, che per tanto tempo mi legarono a RomaF\u00fcr die Arbeit an seiner \u201eGeschichte der Stadt Rom im Mittelalter\u201c (8 Bde., 1859\u20131872) und seine anderen historischen Arbeiten hatte er 22 Jahre, von 1852\u20131874, in Italien verbracht; siehe dazu den Brief von Gregorovius an Ersilia Caetani Lovatelli vom 15.11.1874., non dispero di poter ritornare in Italia ogni anno, per rinnovarmi le mie relazioni, accioch\u00e8 io non troppo presto sia dimenticato in Italia. In quanto a Lei e la gentilissima signora Contessa mi lusingo colla certissima speranza, che Lor Signorie continueranno a serbarmi una memoria benevola. Ho il debito ancora di ringraziarla dell\u2019essersi incaricato di spedirmi l\u2019opuscolo del Conte Carlo PepoliDer in Bologna geborene und ans\u00e4ssige Conte Carlo Pepoli (1796\u20131881) war Dichter und Politiker. Er war seit 1860 Abgeordneter im Parlament der Romagna, seit 1862 Senator des K\u00f6nigreichs und von 1862\u20131866 B\u00fcrgermeister von Bologna. Seit 1860 unterrichtete er Philosophie an der Universit\u00e4t von Bologna und war Sekret\u00e4r der Akademie der Sch\u00f6nen K\u00fcnste. Seine Sammlung bologneser Architekturzeichnungen vermachte er 1863 der Biblioteca Comunale dell\u2019Archiginnasio. Es ist nicht ermittelbar, welche Publikation Pepolis Gregorovius \u00fcber Gozzadini zugegangen war., il quale ringraziai del dono fattomi mediante una lettera, cui quel distinto Signore diede gentilissimo riscontroEs ist kein Brief von Gregorovius an Carlo Pepoli oder ein Gegenbrief erhalten.. \nAugurando a Lor Signorie una perfetta salute e la pi\u00f9 bella villeggiatura in RonzanoZu dem von Gozzadinis in der Villa Ronzano unterhaltenen Salon, in dem auch Gregorovius regelm\u00e4\u00dfig gast war, siehe den Brief von Gregorovius an Giovanni Gozzadini vom 3.11.1856. Nach dem Tod der Gr\u00e4fin Maria widmete Gregorovius dem Salon einen Essay: Die Villa Ronzano. Ein Musensitz der Gozzadini von Bologna (ED in: Nord und S\u00fcd. Eine deutsche Monatsschrift. Bd. 23. Breslau, Berlin: Schottlaender 1882. S. 312\u2013321 \u2013 aufgenommen in: KS Bd. 3, S. 97\u2013120)., mi raffermo con affettuosa venerazione\n\nLor servitor devoto\nFerd. Gregorovius\n\n\n"
}