{
    "filename": "1880-12-12_Amari_Michele",
    "title": "Ferdinand Gregorovius an Michele Amari in Rom. M\u00fcnchen, 12. Dezember 1880 ",
    "sent": {
        "date": {
            "when": "1880-12-12",
            "cert": "high"
        },
        "person": {
            "name": "Gregorovius, Ferdinand (1821-1891)",
            "key": "G001200"
        },
        "place": {
            "name": "M\u00fcnchen",
            "key": "G000734"
        }
    },
    "received": null,
    "plain": "\n\n\nMonaco 12. Dicembre 80.\nGentilissimo ed illustre amico,\n\nLe rendo infinite grazie della premura, con la quale Ella ha corrisposto alle mie domande10 Tage zuvor hatte Gregorovius ein Schreiben an Amari gerichtet, in dem er den ausgewiesenen Orientalisten um Informationen zu arabischen Schriftstellern und Geografen, die sich zu Athen ge\u00e4u\u00dfert haben, bittet; siehe den Brief von Gregorovius an Michele Amari vom 2.12.1880. Ein Vermerk auf diesem Brief l\u00e4sst darauf schlie\u00dfen, dass Amari die Anfrage am 9. Dezember beantwortet hat; das Schreiben ist allerdings nicht erhalten.. Sono lieto di poter far profitto delle sue notizie, per iscarse che siano. Per altro non mene meraviglio punto, imperocch\u00e8 il fiumicello della storia di Atene nel medio evoEr arbeitete an einem Aufsatz mit dem Titel \u201eAthen in den dunklen Jahrhunderten\u201c, der 1881in der Zeitschrift \u201eUnsere Zeit\u201c erscheinen sollte. corra pi\u00f9 scarso ancora dello stesso IlissoDer Ilisos ist ein kleiner, kaum wasserreicher Fluss, der durch die Athen-Ebene flie\u00dft.. Per la qual cosa il celebre FallmeraierDer Orientalist und Publizist Jakob Philipp Fallmerayer (1790\u20131861) hatte zun\u00e4chst an der Universit\u00e4t Landshut studiert und war von dort an die Universit\u00e4t in Salzburg gegangen, wo er sich orientalischen Sprachen widmete. Nach einer T\u00e4tigkeit in der bayerischen Armee, lie\u00df er sich als Privatdozent in Lindau nieder. Von 1826\u20131848 war er Professor an der Universit\u00e4t M\u00fcnchen f\u00fcr Philologie und Universalhistorie. Von 1831\u20131834 befand er sich auf einer Forschungsreise durch Griechenland. Zur\u00fcck in M\u00fcnchen arbeitete er wieder als Privatdozent und Publizist f\u00fcr die Allgemeine Zeitung. Zu Fallmerayers wichtigsten Studien z\u00e4hlen seine \u201eFragmente aus dem Orient\u201c (2 Bde., Stuttgart: Cotta 1845). Zur Bedeutung Fallmerayers f\u00fcr Gregorovius\u2019 Griechenlandstudien siehe den Brief von Gregorovius an Ersilia Caetani Lovatelli vom 26.11.1876. non esit\u00f2 protestare, esser rimasta la citt\u00e0 di PericleStaatsmann und Stratege im klassischen Athen. deserta per il corso di tre o quattro secoli. \nIl Hammer cita alcuni scrittori TurchiDer \u00f6sterreichische Diplomat und Orientalist Joseph von Hammer-Purgstall (1774\u20131856) war vor allem als \u00dcbersetzer orientalischer Schriften bekannt geworden. Mit seiner breit angelegten \u201eGeschichte des osmanischen Reiches\u201c in zehn B\u00e4nden (Pest: C. A. Hartleben 1827\u20131835) erlangte er noch mehr Bekanntheit. Seinen Tod vermerkte Gregorovius im Tagebuch (siehe RT, Rom, letzter Tag des Jahres 1856, S. 65)., che fanno menzione di Atene, ma non m\u2019importa tanto il saperne, perch\u00e8 sono di et\u00e0 pi\u00f9ttosto recente. Ho esaminato molti viaggi de\u2019 pellegrini, le croniche del medio evo, le Acta SanctorumDie \u00e4lteres Wissen \u00fcber M\u00e4rtyrer und Heilige der griechischen und katholischen Kirche vereinende Legendensammlungen, die bereits seit Ende des 15. Jahrhunderts herausgegeben wurden. , gli scrittori Bizantini, il Ramon MuntanerDer Katalane Ramon Muntaner (1265\u20131336) war einer der bedeutenden Chronist des Sp\u00e4tmittelalters. Er schrieb in den Jahren von 1325\u20131328 eine \u201eCr\u00f2nica\u201c \u00fcber den Aufstieg der katalanisch-aragonesischen Dynastie, die in Teilen auf seinen eigenen Erlebnissen beruht., le Bolle de\u2019 Papi, e diverse altre cose, e ho potuto cavarne tanto materiale da illustrare discretamente bene la quistione in proposito. Mi son rivolto pure ad un amico mio assai dotto in Cristiania, Christiana war von 1624\u20131924 der Name der norwegischen Hauptsadt Oslo. Nicht ermittelt, um wen es sich hier handelt. Gregorovius\u2019 norwegischer Freund, der Historiker Peter Andreas Munch (*1810), der 1858 gekommen war, war bereits 1863 verstorben (siehe RT, 17.5.\u201324.6.1863. S. 160\u2013162).per informarmi di tutto ci\u00f2, che si trova scritto a proposito di Atene nelle Sagas dell\u2019 IslandiaDie Isl\u00e4ndersagas geh\u00f6ren zur isl\u00e4ndischen Sagaliteratur und thematisch zur altnordischen Literatur. Dabei handelt sich um anonym verfasste gr\u00f6\u00dfere Prosawerke und kurze Erz\u00e4hlungen aus der Zeit ab 1200 bis ins 14. Jahrhundert.. Ella si ricorder\u00e0 del fatto assai curioso, che il leone del PireoDer aus Pir\u00e4us, Gemeinde in der griechischen Region Attika und Hafenstadt Athens, stammende, antike und drei Meter hohe Marmorl\u00f6we wurde um 360 v. Chr geschaffen und kam 1688 als Kriegsbeute nach Venedig.  fatto collocare dal MonsiniDer 108. Doge von Venedig, Francesco Morosini (1618\u20131694), hatte die Regenschaft von 1688\u20131694 inne und machte sich als F\u00fchrer der venezianischen Truppen einen Namen, die er im Krieg gegen das Osmanische Reich anf\u00fchrte. W\u00e4hrend der Belagerung von Pir\u00e4us im Gro\u00dfen T\u00fcrkenkrieg durch Morosini und seine M\u00e4nner 1687 fiel der Marmorl\u00f6we in den Besitz der Eindringlinge. Einschu\u00dfl\u00f6cher im L\u00f6wen belegen, dass es zu k\u00e4mpferischen Auseinandersetzungen kam. dinanzi all\u2019 Arsenale di Venezia, dove ancora si trova, porta sul suo dorso iscrizioni runiche, scolpitevi dai VarangiDie War\u00e4gergarde ist die zumindest anfangs aus skandinavischen Wikingern formierte Leibgarde des byzantinischen Kaisers. circa l\u2019anno 1048, come ha dimostrato il Rafn, interpretatore delle medesimeCarl Christian Rafn (1795\u20131864), d\u00e4nischer Arch\u00e4ologe, machte die nordischen Sagas weltbekannt. Die Entzifferung der auf dem L\u00f6we von Pir\u00e4us eingeritzten, stark abgenutzten und deshalb schwer deutbaren Runen publizierte Rafn 1857: En Nordisk Runeindskrift i Pir\u00e6eus, med Forklaring af C. C. Rafn. In: Antiquarisk Tidsskrift: Udgivet af det Kongelige Nordiske Oldskrift-Selskab 1855\u201357. 1859, S. 3\u201369: https://books.google.it/books?id=7khBAAAAYAAJ&printsec=frontcover&source=gbs_ge_summary_r&redir_esc=y#v=onepage&q&f=true..\nChiudo la lettera, per non darle troppo fastidio. Tanti saluti cordiali a lei e alla sua gentilissima famiglia, e buone feste con ogni cosa bella che desiderar si possa.\n\nFerd. Gregorovius\n\n\n"
}